slurm_longrun/__init__.py
slurm_longrun/cli.py
slurm_longrun/common.py
slurm_longrun/logger.py
slurm_longrun/runner.py
slurm_longrun/utils.py
slurm_longrun-0.1.4.dist-info/METADATA
slurm_longrun-0.1.4.dist-info/WHEEL
slurm_longrun-0.1.4.dist-info/entry_points.txt
slurm_longrun-0.1.4.dist-info/RECORD
